README.rst
setup.py
prosemirror/__init__.py
prosemirror/js_lib.py
prosemirror_python.egg-info/PKG-INFO
prosemirror_python.egg-info/SOURCES.txt
prosemirror_python.egg-info/dependency_links.txt
prosemirror_python.egg-info/requires.txt
prosemirror_python.egg-info/top_level.txt