Metadata-Version: 1.1
Name: prosemirror-python
Version: 0.0.4
Summary: Python translation of prosemirror parts needed to modify a document in Python
Home-page: https://www.github.org/fiduswriter/prosemirror-python
Author: Johannes Wilm
Author-email: johannes@fiduswriter.org
License: AGPL License
Platform: UNKNOWN
Classifier: Environment :: Web Environment
Classifier: Intended Audience :: Developers
Classifier: License :: OSI Approved :: GNU Affero General Public License v3
Classifier: Operating System :: OS Independent
Classifier: Programming Language :: Python
Classifier: Programming Language :: Python :: 2.7
Classifier: Programming Language :: Python :: 3.6
Classifier: Topic :: Internet :: WWW/HTTP
Classifier: Topic :: Internet :: WWW/HTTP :: Dynamic Content
